Metadata-Version: 2.1
Name: django-env-context-processor
Version: 2020.7.1
Summary: Django env context processor
Home-page: https://github.com/andrewp-as-is/django-env-context-processor.py
License: Unlicense
Keywords: Django env context processor
Platform: UNKNOWN
Classifier: Framework :: Django
Classifier: License :: Public Domain
Classifier: Operating System :: OS Independent
Classifier: Programming Language :: Python :: 3
